nomad_camels_driver_ADALM1000/ADALM1000.py
nomad_camels_driver_ADALM1000/ADALM1000_ophyd.py
nomad_camels_driver_ADALM1000/__init__.py
nomad_camels_driver_ADALM1000-0.1.0.dist-info/LICENSE
nomad_camels_driver_ADALM1000-0.1.0.dist-info/METADATA
nomad_camels_driver_ADALM1000-0.1.0.dist-info/WHEEL
nomad_camels_driver_ADALM1000-0.1.0.dist-info/top_level.txt
nomad_camels_driver_ADALM1000-0.1.0.dist-info/RECORD
