Metadata-Version: 2.1
Name: nomad_camels_driver_ADALM1000
Version: 0.1.0
Summary: Instrument driver for ADALM1000 for NOMAD CAMELS
Author-email: enter your name here! <contact@email.com>
Project-URL: NOMAD Camels GitHub, https://github.com/FAU-LAP/NOMAD-CAMELS
Project-URL: CAMELS Drivers GitHub, https://github.com/FAU-LAP/CAMELS_drivers
Project-URL: NOMAD Camels Documentation, https://fau-lap.github.io/NOMAD-CAMELS/doc/instruments/instruments.html
Classifier: Programming Language :: Python :: 3
Classifier: License :: OSI Approved :: GNU Lesser General Public License v2 (LGPLv2)
Requires-Python: >=3.9.6
License-File: LICENSE
Requires-Dist: nomad-camels
Requires-Dist: pysmu
